bguploaderlocal/__init__.py
bguploaderlocal/check_version.py
bguploaderlocal/cli.py
bguploaderlocal/config.py
bguploaderlocal/uploader.py
bguploaderlocal-0.0.28.dist-info/METADATA
bguploaderlocal-0.0.28.dist-info/WHEEL
bguploaderlocal-0.0.28.dist-info/entry_points.txt
bguploaderlocal-0.0.28.dist-info/top_level.txt
bguploaderlocal-0.0.28.dist-info/RECORD
